abx_spec_archivebox/__init__.py
abx_spec_archivebox/effects.py
abx_spec_archivebox/events.py
abx_spec_archivebox/states.py
abx_spec_archivebox/writes.py
abx_spec_archivebox-0.1.0.dist-info/METADATA
abx_spec_archivebox-0.1.0.dist-info/WHEEL
abx_spec_archivebox-0.1.0.dist-info/entry_points.txt
abx_spec_archivebox-0.1.0.dist-info/RECORD
