Metadata-Version: 2.4
Name: abx-spec-archivebox
Version: 0.1.0
Summary: The common shared interfaces for the ABX ArchiveBox plugin ecosystem.
Requires-Python: >=3.10
Requires-Dist: abx>=0.1.0
Requires-Dist: django<6.0,>=5.1.1
